rosolve/__init__.py
rosolve/client.py
rosolve/errors.py
rosolve/types.py
rosolve-1.1.1.dist-info/METADATA
rosolve-1.1.1.dist-info/WHEEL
rosolve-1.1.1.dist-info/top_level.txt
rosolve-1.1.1.dist-info/RECORD
