Metadata-Version: 2.2
Name: rosolve
Version: 1.1.1
Summary: An async Python client for the RoSolve API
Author-email: SillyVoidi <nothanks@email.com>
Project-URL: Homepage, https://github.com/yourusername/rosolve
Keywords: rosolve,captcha,roblox,funcaptcha
Classifier: Programming Language :: Python :: 3
Classifier: Programming Language :: Python :: 3.7
Classifier: Programming Language :: Python :: 3.8
Classifier: Programming Language :: Python :: 3.9
Classifier: Programming Language :: Python :: 3.10
Classifier: Programming Language :: Python :: 3.11
Classifier: Operating System :: OS Independent
Classifier: Development Status :: 5 - Production/Stable
Requires-Python: >=3.7
Requires-Dist: aiohttp>=3.8.0
Requires-Dist: curl_cffi>=0.5.0
Requires-Dist: colorama>=0.4.6
